pygtftk/arg_formatter.py
pygtftk/version.py
pygtftk/tab_interface.py
pygtftk/settings.py
pygtftk/biomart.py
pygtftk/Line.py
pygtftk/cmd_object.py
pygtftk/utils.py
pygtftk/fasta_interface.py
pygtftk/gtf_interface.py
pygtftk/cmd_manager.py
pygtftk/__init__.py
pygtftk/bedtool_extension.py
pygtftk/plugins/add_prefix.py
pygtftk/plugins/nb_transcripts.py
pygtftk/plugins/seqid_list.py
pygtftk/plugins/ologram_merge_runs.py
pygtftk/plugins/select_by_numeric_value.py
pygtftk/plugins/shift.py
pygtftk/plugins/overlapping.py
pygtftk/plugins/count_key_values.py
pygtftk/plugins/exon_size.py
pygtftk/plugins/apropos.py
pygtftk/plugins/select_by_intron_size.py
pygtftk/plugins/get_5p_3p_coords.py
pygtftk/plugins/discretize_key.py
pygtftk/plugins/ologram.py
pygtftk/plugins/get_attr_list.py
pygtftk/plugins/retrieve.py
pygtftk/plugins/convert_ensembl.py
pygtftk/plugins/random_tx.py
pygtftk/plugins/great_reg_domains.py
pygtftk/plugins/intronic.py
pygtftk/plugins/intergenic.py
pygtftk/plugins/select_by_regexp.py
pygtftk/plugins/rm_dup_tss.py
pygtftk/plugins/control_list.py
pygtftk/plugins/tss_dist.py
pygtftk/plugins/mk_matrix.py
pygtftk/plugins/convergent.py
pygtftk/plugins/add_exon_nb.py
pygtftk/plugins/select_by_nb_exon.py
pygtftk/plugins/ologram_modl_treeify.py
pygtftk/plugins/get_example.py
pygtftk/plugins/random_list.py
pygtftk/plugins/feat_size.py
pygtftk/plugins/tabulate.py
pygtftk/plugins/profile.py
pygtftk/plugins/divergent.py
pygtftk/plugins/select_most_5p_tx.py
pygtftk/plugins/join_multi_file.py
pygtftk/plugins/coverage.py
pygtftk/plugins/ologram_merge_stats.py
pygtftk/plugins/bigwig_to_bed.py
pygtftk/plugins/count.py
pygtftk/plugins/select_by_max_exon_nb.py
pygtftk/plugins/tss_numbering.py
pygtftk/plugins/get_feat_seq.py
pygtftk/plugins/get_ceas_records.py
pygtftk/plugins/get_tx_seq.py
pygtftk/plugins/select_by_go.py
pygtftk/plugins/select_by_key.py
pygtftk/plugins/splicing_site.py
pygtftk/plugins/merge_attr.py
pygtftk-1.6.2.dist-info/METADATA
pygtftk-1.6.2.dist-info/RECORD
pygtftk-1.6.2.dist-info/WHEEL
pygtftk-1.6.2.dist-info/top_level.txt
pygtftk-1.6.2.dist-info/LICENSE
