Metadata-Version: 2.1
Name: pygtftk
Version: 1.6.2
Summary: The Python GTF toolkit (pygtftk) package: easy handling of GTF files
Home-page: https://github.com/dputhier/pygtftk
Author: Fabrice LOPEZ, Denis PUTHIER and Quentin FERRE
Author-email: denis.puthier@univ-amu.fr
License: LICENSE.txt
Project-URL: Source, https://github.com/dputhier/pygtftk
Project-URL: Tracker, https://github.com/dputhier/pygtftk
Keywords: genomics bioinformatics GTF BED
Platform: UNKNOWN
Classifier: License :: OSI Approved :: MIT License
Classifier: Operating System :: MacOS
Classifier: Operating System :: POSIX :: Linux
Classifier: Development Status :: 4 - Beta
Classifier: Environment :: Console
Classifier: Programming Language :: Python :: 3.9
Classifier: Intended Audience :: Science/Research
Classifier: Natural Language :: English
Classifier: Topic :: Scientific/Engineering :: Bio-Informatics
Classifier: Operating System :: POSIX :: Linux
Classifier: Operating System :: MacOS
Classifier: Topic :: Documentation :: Sphinx
Requires-Python: >=3.9,<3.10
Requires-Dist: GitPython (>=2.1.8)
Requires-Dist: biopython (>=1.78)
Requires-Dist: cffi (>=1.10.0)
Requires-Dist: cloudpickle
Requires-Dist: cython (>=0.29.21)
Requires-Dist: ftputil (>=4.0.0)
Requires-Dist: graphviz
Requires-Dist: matplotlib (>=3.3.1)
Requires-Dist: mpmath (>=1.1.0)
Requires-Dist: nose
Requires-Dist: numpy (>=1.19.1)
Requires-Dist: pandas (>=1.1.2)
Requires-Dist: plotnine (>=0.7.1)
Requires-Dist: pybedtools (>=0.8.1)
Requires-Dist: pybigwig (>=0.3.17)
Requires-Dist: pyparsing (>=2.2.0)
Requires-Dist: pyyaml
Requires-Dist: pysam (>=0.17.0)
Requires-Dist: pillow (<=8.3.2,>=7.0.0)
Requires-Dist: requests (>=2.23.0)
Requires-Dist: scikit-learn (>=0.24)
Requires-Dist: scipy (>=1.5.2)
Requires-Dist: seaborn
Requires-Dist: setuptools
Requires-Dist: billiard (>=3.6.4.0)
Provides-Extra: dev
Requires-Dist: pycodestyle (>=2.1.0) ; extra == 'dev'
Requires-Dist: sphinx (>=1.5.2) ; extra == 'dev'
Requires-Dist: sphinxcontrib-programoutput (>=0.8) ; extra == 'dev'
Requires-Dist: sphinx-bootstrap-theme (>=0.4.9) ; extra == 'dev'
Requires-Dist: sphinxcontrib-googleanalytics ; extra == 'dev'
Requires-Dist: twine (>=3.4.1) ; extra == 'dev'
Provides-Extra: gffutils
Requires-Dist: gffutils ; extra == 'gffutils'
